{
    "Battery_Modell": "Li-ion BL26650",
    "Nominal Capacity": "6800mAH",
    "Nominal Voltage": 3.7,
    "Charging":{
        "charge_voltage": 3.7,
        "charge_current": 3.4,
        "stop_voltage":   4.2,
        "stop_current":   5.0,
        "stop_capacity":  5.44,
        "stop_time":      120
    },

    "Discharge":{
        "dicharge_voltage": 3.7,
        "discharge_current": 3.4,
        "stop_voltage":   4.2,
        "stop_current":   5.0,
        "stop_capacity":  5.44,
        "stop_time":      120
    }
}